[
    {
        "Player": "Walter",
        "Nation": "brBRA",
        "Pos": "GK",
        "Age": "36-306",
        "90s": "24.0",
        "SCA": "6",
        "SCA90": "0.25",
        "PassLive": "1",
        "PassDead": "1",
        "TO": "0",
        "Sh": "0",
        "Fld": "0",
        "Def": "0",
        "GCA": "2",
        "GCA90": "0.08",
        "Matches": "Matches"
    },
    {
        "Player": "Marllon Borges",
        "Nation": "brBRA",
        "Pos": "DF",
        "Age": "32-156",
        "90s": "23.0",
        "SCA": "15",
        "SCA90": "0.65",
        "PassLive": "0",
        "PassDead": "0",
        "TO": "0",
        "Sh": "0",
        "Fld": "1",
        "Def": "0",
        "GCA": "1",
        "GCA90": "0.04",
        "Matches": "Matches"
    },
    {
        "Player": "Isidro Pitta",
        "Nation": "pyPAR",
        "Pos": "FW",
        "Age": "25-036",
        "90s": "21.3",
        "SCA": "42",
        "SCA90": "1.97",
        "PassLive": "1",
        "PassDead": "0",
        "TO": "1",
        "Sh": "0",
        "Fld": "1",
        "Def": "0",
        "GCA": "3",
        "GCA90": "0.14",
        "Matches": "Matches"
    },
    {
        "Player": "Alan Empereur",
        "Nation": "brBRA",
        "Pos": "DF",
        "Age": "30-193",
        "90s": "20.8",
        "SCA": "28",
        "SCA90": "1.35",
        "PassLive": "1",
        "PassDead": "0",
        "TO": "0",
        "Sh": "0",
        "Fld": "0",
        "Def": "0",
        "GCA": "1",
        "GCA90": "0.05",
        "Matches": "Matches"
    },
    {
        "Player": "Lucas Mineiro",
        "Nation": "brBRA",
        "Pos": "MF",
        "Age": "28-208",
        "90s": "19.9",
        "SCA": "25",
        "SCA90": "1.26",
        "PassLive": "1",
        "PassDead": "0",
        "TO": "0",
        "Sh": "1",
        "Fld": "0",
        "Def": "0",
        "GCA": "2",
        "GCA90": "0.10",
        "Matches": "Matches"
    },
    {
        "Player": "Denilson",
        "Nation": "brBRA",
        "Pos": "MF",
        "Age": "23-180",
        "90s": "16.5",
        "SCA": "60",
        "SCA90": "3.64",
        "PassLive": "6",
        "PassDead": "0",
        "TO": "1",
        "Sh": "0",
        "Fld": "0",
        "Def": "0",
        "GCA": "7",
        "GCA90": "0.42",
        "Matches": "Matches"
    },
    {
        "Player": "Ramon",
        "Nation": "brBRA",
        "Pos": "DF",
        "Age": "23-190",
        "90s": "17.4",
        "SCA": "42",
        "SCA90": "2.42",
        "PassLive": "1",
        "PassDead": "0",
        "TO": "0",
        "Sh": "0",
        "Fld": "0",
        "Def": "0",
        "GCA": "1",
        "GCA90": "0.06",
        "Matches": "Matches"
    },
    {
        "Player": "Matheus Alexandre",
        "Nation": "brBRA",
        "Pos": "DF",
        "Age": "25-165",
        "90s": "16.3",
        "SCA": "24",
        "SCA90": "1.48",
        "PassLive": "0",
        "PassDead": "1",
        "TO": "0",
        "Sh": "0",
        "Fld": "0",
        "Def": "0",
        "GCA": "1",
        "GCA90": "0.06",
        "Matches": "Matches"
    },
    {
        "Player": "Clayson",
        "Nation": "brBRA",
        "Pos": "FW,MF",
        "Age": "29-184",
        "90s": "12.5",
        "SCA": "29",
        "SCA90": "2.33",
        "PassLive": "1",
        "PassDead": "1",
        "TO": "1",
        "Sh": "0",
        "Fld": "2",
        "Def": "0",
        "GCA": "5",
        "GCA90": "0.40",
        "Matches": "Matches"
    },
    {
        "Player": "Jonathan Cafu",
        "Nation": "brBRA",
        "Pos": "FW,MF",
        "Age": "33-071",
        "90s": "13.1",
        "SCA": "34",
        "SCA90": "2.59",
        "PassLive": "2",
        "PassDead": "0",
        "TO": "0",
        "Sh": "1",
        "Fld": "0",
        "Def": "0",
        "GCA": "3",
        "GCA90": "0.23",
        "Matches": "Matches"
    },
    {
        "Player": "Max",
        "Nation": "brBRA",
        "Pos": "MF",
        "Age": "23-130",
        "90s": "11.2",
        "SCA": "39",
        "SCA90": "3.48",
        "PassLive": "3",
        "PassDead": "2",
        "TO": "0",
        "Sh": "0",
        "Fld": "0",
        "Def": "0",
        "GCA": "5",
        "GCA90": "0.45",
        "Matches": "Matches"
    },
    {
        "Player": "Fernando Sobral",
        "Nation": "brBRA",
        "Pos": "MF",
        "Age": "29-277",
        "90s": "12.6",
        "SCA": "38",
        "SCA90": "3.01",
        "PassLive": "2",
        "PassDead": "1",
        "TO": "0",
        "Sh": "0",
        "Fld": "0",
        "Def": "0",
        "GCA": "3",
        "GCA90": "0.24",
        "Matches": "Matches"
    },
    {
        "Player": "Bruno Fabiano Alves",
        "Nation": "brBRA",
        "Pos": "DF",
        "Age": "33-156",
        "90s": "10.4",
        "SCA": "9",
        "SCA90": "0.87",
        "PassLive": "1",
        "PassDead": "0",
        "TO": "0",
        "Sh": "0",
        "Fld": "0",
        "Def": "0",
        "GCA": "1",
        "GCA90": "0.10",
        "Matches": "Matches"
    },
    {
        "Player": "Derik Lacerda",
        "Nation": "brBRA",
        "Pos": "FW,MF",
        "Age": "24-358",
        "90s": "10.4",
        "SCA": "27",
        "SCA90": "2.60",
        "PassLive": "0",
        "PassDead": "0",
        "TO": "0",
        "Sh": "0",
        "Fld": "0",
        "Def": "0",
        "GCA": "0",
        "GCA90": "0.00",
        "Matches": "Matches"
    },
    {
        "Player": "Railan",
        "Nation": "brBRA",
        "Pos": "DF,FW",
        "Age": "24-193",
        "90s": "8.9",
        "SCA": "21",
        "SCA90": "2.35",
        "PassLive": "1",
        "PassDead": "0",
        "TO": "0",
        "Sh": "1",
        "Fld": "0",
        "Def": "0",
        "GCA": "2",
        "GCA90": "0.22",
        "Matches": "Matches"
    },
    {
        "Player": "Lucas Fernandes",
        "Nation": "brBRA",
        "Pos": "MF,FW",
        "Age": "26-365",
        "90s": "6.6",
        "SCA": "18",
        "SCA90": "2.73",
        "PassLive": "0",
        "PassDead": "0",
        "TO": "0",
        "Sh": "0",
        "Fld": "0",
        "Def": "0",
        "GCA": "0",
        "GCA90": "0.00",
        "Matches": "Matches"
    },
    {
        "Player": "Rikelme",
        "Nation": "brBRA",
        "Pos": "DF",
        "Age": "21-065",
        "90s": "5.5",
        "SCA": "6",
        "SCA90": "1.09",
        "PassLive": "0",
        "PassDead": "0",
        "TO": "0",
        "Sh": "0",
        "Fld": "0",
        "Def": "0",
        "GCA": "0",
        "GCA90": "0.00",
        "Matches": "Matches"
    },
    {
        "Player": "Filipe Augusto",
        "Nation": "brBRA",
        "Pos": "MF",
        "Age": "31-038",
        "90s": "4.3",
        "SCA": "6",
        "SCA90": "1.38",
        "PassLive": "1",
        "PassDead": "0",
        "TO": "0",
        "Sh": "0",
        "Fld": "0",
        "Def": "0",
        "GCA": "1",
        "GCA90": "0.23",
        "Matches": "Matches"
    },
    {
        "Player": "Juan Pablo",
        "Nation": "brBRA",
        "Pos": "DF",
        "Age": "22-147",
        "90s": "2.8",
        "SCA": "2",
        "SCA90": "0.72",
        "PassLive": "0",
        "PassDead": "0",
        "TO": "0",
        "Sh": "0",
        "Fld": "0",
        "Def": "0",
        "GCA": "0",
        "GCA90": "0.00",
        "Matches": "Matches"
    },
    {
        "Player": "André Luis",
        "Nation": "brBRA",
        "Pos": "FW,MF",
        "Age": "27-151",
        "90s": "4.6",
        "SCA": "9",
        "SCA90": "1.95",
        "PassLive": "0",
        "PassDead": "0",
        "TO": "0",
        "Sh": "0",
        "Fld": "0",
        "Def": "0",
        "GCA": "0",
        "GCA90": "0.00",
        "Matches": "Matches"
    },
    {
        "Player": "Deyverson",
        "Nation": "brBRA",
        "Pos": "FW",
        "Age": "33-134",
        "90s": "2.4",
        "SCA": "2",
        "SCA90": "0.82",
        "PassLive": "0",
        "PassDead": "0",
        "TO": "1",
        "Sh": "0",
        "Fld": "0",
        "Def": "0",
        "GCA": "1",
        "GCA90": "0.41",
        "Matches": "Matches"
    },
    {
        "Player": "Gabriel Knesowitsch",
        "Nation": "brBRA",
        "Pos": "DF",
        "Age": "20-337",
        "90s": "2.2",
        "SCA": "3",
        "SCA90": "1.37",
        "PassLive": "0",
        "PassDead": "0",
        "TO": "0",
        "Sh": "0",
        "Fld": "0",
        "Def": "0",
        "GCA": "0",
        "GCA90": "0.00",
        "Matches": "Matches"
    },
    {
        "Player": "Eliel Chrystian",
        "Nation": "brBRA",
        "Pos": "FW,MF",
        "Age": "21-237",
        "90s": "3.6",
        "SCA": "7",
        "SCA90": "1.94",
        "PassLive": "0",
        "PassDead": "0",
        "TO": "0",
        "Sh": "0",
        "Fld": "0",
        "Def": "0",
        "GCA": "0",
        "GCA90": "0.00",
        "Matches": "Matches"
    },
    {
        "Player": "Mateus Pasinato",
        "Nation": "brBRA",
        "Pos": "GK",
        "Age": "32-083",
        "90s": "1.0",
        "SCA": "0",
        "SCA90": "0.00",
        "PassLive": "0",
        "PassDead": "0",
        "TO": "0",
        "Sh": "0",
        "Fld": "0",
        "Def": "0",
        "GCA": "0",
        "GCA90": "0.00",
        "Matches": "Matches"
    },
    {
        "Player": "Allyson Aires dos Santos",
        "Nation": "brBRA",
        "Pos": "DF",
        "Age": "33-332",
        "90s": "1.0",
        "SCA": "0",
        "SCA90": "0.00",
        "PassLive": "0",
        "PassDead": "0",
        "TO": "0",
        "Sh": "0",
        "Fld": "0",
        "Def": "0",
        "GCA": "0",
        "GCA90": "0.00",
        "Matches": "Matches"
    },
    {
        "Player": "Guilherme Madruga",
        "Nation": "brBRA",
        "Pos": "MF,FW",
        "Age": "23-313",
        "90s": "1.2",
        "SCA": "5",
        "SCA90": "4.33",
        "PassLive": "1",
        "PassDead": "0",
        "TO": "0",
        "Sh": "0",
        "Fld": "0",
        "Def": "0",
        "GCA": "1",
        "GCA90": "0.87",
        "Matches": "Matches"
    },
    {
        "Player": "Luciano Giménez",
        "Nation": "arARG",
        "Pos": "FW,MF",
        "Age": "24-214",
        "90s": "0.8",
        "SCA": "0",
        "SCA90": "0.00",
        "PassLive": "0",
        "PassDead": "0",
        "TO": "0",
        "Sh": "0",
        "Fld": "0",
        "Def": "0",
        "GCA": "0",
        "GCA90": "0.00",
        "Matches": "Matches"
    },
    {
        "Player": "Gustavo Sauer",
        "Nation": "brBRA",
        "Pos": "MF,FW",
        "Age": "31-142",
        "90s": "0.5",
        "SCA": "3",
        "SCA90": "6.14",
        "PassLive": "0",
        "PassDead": "0",
        "TO": "0",
        "Sh": "0",
        "Fld": "0",
        "Def": "0",
        "GCA": "0",
        "GCA90": "0.00",
        "Matches": "Matches"
    },
    {
        "Player": "Jadson",
        "Nation": "brBRA",
        "Pos": "MF",
        "Age": "19-040",
        "90s": "0.2",
        "SCA": "0",
        "SCA90": "0.00",
        "PassLive": "0",
        "PassDead": "0",
        "TO": "0",
        "Sh": "0",
        "Fld": "0",
        "Def": "0",
        "GCA": "0",
        "GCA90": "0.00",
        "Matches": "Matches"
    },
    {
        "Player": "Squad Total",
        "Nation": "",
        "Pos": "",
        "Age": "28.4",
        "90s": "25.0",
        "SCA": "500",
        "SCA90": "20.00",
        "PassLive": "23",
        "PassDead": "6",
        "TO": "4",
        "Sh": "3",
        "Fld": "4",
        "Def": "0",
        "GCA": "40",
        "GCA90": "1.60",
        "Matches": ""
    },
    {
        "Player": "Opponent Total",
        "Nation": "",
        "Pos": "",
        "Age": "28.2",
        "90s": "25.0",
        "SCA": "610",
        "SCA90": "24.40",
        "PassLive": "42",
        "PassDead": "5",
        "TO": "3",
        "Sh": "8",
        "Fld": "8",
        "Def": "1",
        "GCA": "67",
        "GCA90": "2.68",
        "Matches": ""
    }
]